scene_rir/__init__.py
scene_rir/__main__.py
scene_rir/_version.py
scene_rir/rir.py
scene_rir-2025.13.dist-info/licenses/LICENSE.txt
scene_rir-2025.13.dist-info/METADATA
scene_rir-2025.13.dist-info/WHEEL
scene_rir-2025.13.dist-info/top_level.txt
scene_rir-2025.13.dist-info/RECORD
