Metadata-Version: 2.4
Name: scene-rir
Version: 2025.13
Summary: Room Impulse Response extraction package.
Author-email: Christos Sevastiadis <csevast@auth.gr>
Project-URL: Home, https://sr.ht/~csevast/scene-rir/
Project-URL: Source, https://git.sr.ht/~csevast/scene_rir
Keywords: room impulse response,rir
Classifier: Development Status :: 4 - Beta
Classifier: Environment :: Console
Classifier: Environment :: MacOS X
Classifier: Environment :: Win32 (MS Windows)
Classifier: Intended Audience :: Developers
Classifier: Intended Audience :: Science/Research
Classifier: Natural Language :: English
Classifier: Operating System :: OS Independent
Classifier: Programming Language :: Python
Classifier: Programming Language :: Python :: Implementation :: CPython
Classifier: Topic :: Scientific/Engineering
Requires-Python: >=3.8
License-File: LICENSE.txt
Requires-Dist: numpy
Requires-Dist: scipy
Dynamic: license-file
